opengeotech/__init__.py
opengeotech/soil_mechanics.py
opengeotech/tests/__init__.py
opengeotech/tests/test_soil_mechanics.py
opengeotech-0.1.0.dist-info/LICENSE
opengeotech-0.1.0.dist-info/METADATA
opengeotech-0.1.0.dist-info/WHEEL
opengeotech-0.1.0.dist-info/top_level.txt
opengeotech-0.1.0.dist-info/RECORD
