Metadata-Version: 2.2
Name: opengeotech
Version: 0.1.0
Summary: A simple geotechnical engineering package
Home-page: https://github.com/OpenGeotechnical/opengeotech-python
Author: OpenGeotech Contributors
Author-email: OpenGeotech Contributors <opengeotechnical@gmail.com>
License: MIT
Project-URL: Homepage, https://github.com/OpenGeotechnical/opengeotech-python
Project-URL: Bug Tracker, https://github.com/OpenGeotechnical/opengeotech-python/issues
Classifier: Programming Language :: Python :: 3
Classifier: License :: OSI Approved :: MIT License
Classifier: Operating System :: OS Independent
Classifier: Topic :: Scientific/Engineering
Requires-Python: >=3.6
License-File: LICENSE
Dynamic: author
Dynamic: home-page
Dynamic: requires-python
